hoodpay/__init__.py
hoodpay/hoodpay.py
hoodpay/types/__init__.py
hoodpay/types/directcryptocharge.py
hoodpay/types/payment.py
HoodPay-0.0.1.dist-info/METADATA
HoodPay-0.0.1.dist-info/WHEEL
HoodPay-0.0.1.dist-info/top_level.txt
HoodPay-0.0.1.dist-info/RECORD
